PyRlEnvs/BaseEnvironment.py
PyRlEnvs/Category.py
PyRlEnvs/FiniteDynamics.py
PyRlEnvs/__init__.py
PyRlEnvs/py.typed
PyRlEnvs/registry.py
PyRlEnvs/domains/Acrobot.py
PyRlEnvs/domains/BECounterexample.py
PyRlEnvs/domains/BairdCounterexample.py
PyRlEnvs/domains/BoyanChain.py
PyRlEnvs/domains/Cartpole.py
PyRlEnvs/domains/CliffWorld.py
PyRlEnvs/domains/FourRooms.py
PyRlEnvs/domains/HIVTreatment.py
PyRlEnvs/domains/KolterCounterexample.py
PyRlEnvs/domains/MountainCar.py
PyRlEnvs/domains/PuddleWorld.py
PyRlEnvs/domains/RandomWalk.py
PyRlEnvs/domains/__init__.py
PyRlEnvs/domains/GridWorld/Elements.py
PyRlEnvs/domains/GridWorld/GridWorld.py
PyRlEnvs/domains/GridWorld/__init__.py
PyRlEnvs/domains/GridWorld/utils.py
PyRlEnvs/domains/mazes/Wilson.py
PyRlEnvs/domains/mazes/__init__.py
PyRlEnvs/utils/RandomVariables.py
PyRlEnvs/utils/__init__.py
PyRlEnvs/utils/distributions.py
PyRlEnvs/utils/math.py
PyRlEnvs/utils/numerical.py
PyRlEnvs/utils/random.py
pyrlenvs_andnp-2.0.2.dist-info/METADATA
pyrlenvs_andnp-2.0.2.dist-info/WHEEL
pyrlenvs_andnp-2.0.2.dist-info/RECORD
